seismutils/__init__.py
seismutils/geo.py
seismutils/signal.py
seismutils-0.3.1.dist-info/LICENSE
seismutils-0.3.1.dist-info/METADATA
seismutils-0.3.1.dist-info/WHEEL
seismutils-0.3.1.dist-info/top_level.txt
seismutils-0.3.1.dist-info/RECORD
