Metadata-Version: 2.1
Name: seismutils
Version: 0.3.1
Summary: An open-source Python toolkit offering a collection of efficient, easy-to-use functions for seismic data analysis.
Home-page: https://github.com/gabrielepaoletti/seismutils
Download-URL: https://github.com/gabrielepaoletti/seismutils
Author: Gabriele Paoletti
Author-email: gabriele.paoletti@uniroma1.it
License: MIT
Keywords: seismology earthquake geophysics data-analysis
Requires-Python: >=3.11
License-File: LICENSE
Requires-Dist: matplotlib
Requires-Dist: numpy
Requires-Dist: pandas
Requires-Dist: pyproj
Requires-Dist: scipy
Requires-Dist: tqdm
